igs_tools/__init__.py
igs_tools/connection.py
igs_tools/directory.py
igs_tools/utils.py
igs_tools/defines/__init__.py
igs_tools/defines/constellation.py
igs_tools/defines/data_center.py
igs_tools/defines/rinex.py
slm/__init__.py
slm/admin.py
slm/apps.py
slm/authentication.py
slm/context.py
slm/forms.py
slm/manage.py
slm/middleware.py
slm/signals.py
slm/singleton.py
slm/urls.py
slm/utils.py
slm/validators.py
slm/views.py
slm/widgets.py
slm/wsgi.py
slm/api/fields.py
slm/api/filter.py
slm/api/pagination.py
slm/api/permissions.py
slm/api/serializers.py
slm/api/views.py
slm/api/edit/__init__.py
slm/api/edit/serializers.py
slm/api/edit/views.py
slm/api/public/__init__.py
slm/api/public/serializers.py
slm/api/public/views.py
slm/bin/__init__.py
slm/bin/startproject.py
slm/bin/templates/{{ project_dir }}/pyproject.toml
slm/bin/templates/{{ project_dir }}/src/sites/__init__.py
slm/bin/templates/{{ project_dir }}/src/sites/{{ site }}/__init__.py
slm/bin/templates/{{ project_dir }}/src/sites/{{ site }}/base.py
slm/bin/templates/{{ project_dir }}/src/sites/{{ site }}/manage.py
slm/bin/templates/{{ project_dir }}/src/sites/{{ site }}/urls.py
slm/bin/templates/{{ project_dir }}/src/sites/{{ site }}/validation.py
slm/bin/templates/{{ project_dir }}/src/sites/{{ site }}/develop/__init__.py
slm/bin/templates/{{ project_dir }}/src/sites/{{ site }}/develop/local.py
slm/bin/templates/{{ project_dir }}/src/sites/{{ site }}/develop/wsgi.py
slm/bin/templates/{{ project_dir }}/src/sites/{{ site }}/production/__init__.py
slm/bin/templates/{{ project_dir }}/src/sites/{{ site }}/production/wsgi.py
slm/bin/templates/{{ project_dir }}/src/{{ extension_app }}/__init__.py
slm/bin/templates/{{ project_dir }}/src/{{ extension_app }}/admin.py
slm/bin/templates/{{ project_dir }}/src/{{ extension_app }}/apps.py
slm/bin/templates/{{ project_dir }}/src/{{ extension_app }}/models.py
slm/bin/templates/{{ project_dir }}/src/{{ extension_app }}/urls.py
igs_slm-0.4.1b0.dist-info/METADATA
igs_slm-0.4.1b0.dist-info/WHEEL
igs_slm-0.4.1b0.dist-info/entry_points.txt
igs_slm-0.4.1b0.dist-info/licenses/LICENSE
igs_slm-0.4.1b0.dist-info/RECORD
