Metadata-Version: 2.4
Name: igs-slm
Version: 0.4.1b0
Summary: IGS Site Log Manager
Project-URL: Homepage, https://igs-slm.readthedocs.io
Project-URL: Documentation, https://igs-slm.readthedocs.io
Project-URL: Repository, https://github.com/International-GNSS-Service/SLM
Project-URL: Issues, https://github.com/International-GNSS-Service/SLM/issues
Project-URL: Changelog, https://igs-slm.readthedocs.io/en/latest/changelog.html
Author-email: Brian Kohan <bkohan@jpl.nasa.gov>, Ashley Santiago <ashley.k.santiago@jpl.nasa.gov>, Robert Khachikyan <robert.khachikyan@jpl.nasa.gov>
License-Expression: MIT
License-File: LICENSE
Keywords: BeiDou,GLONASS,GNSS,GPS,Galileo,IGS,International GNSS Service,QZSS,SLM,Site Log Manager
Classifier: Development Status :: 4 - Beta
Classifier: Environment :: Web Environment
Classifier: Framework :: Django
Classifier: Framework :: Django :: 4.2
Classifier: Intended Audience :: Developers
Classifier: License :: OSI Approved :: MIT License
Classifier: Natural Language :: English
Classifier: Operating System :: OS Independent
Classifier: Programming Language :: Python
Classifier: Programming Language :: Python :: 3.8
Classifier: Programming Language :: Python :: 3.9
Classifier: Programming Language :: Python :: 3.10
Classifier: Programming Language :: Python :: 3.11
Classifier: Programming Language :: Python :: 3.12
Classifier: Programming Language :: Python :: 3.13
Classifier: Topic :: Internet :: WWW/HTTP
Classifier: Topic :: Internet :: WWW/HTTP :: Site Management
Classifier: Topic :: Software Development :: Libraries
Classifier: Topic :: Software Development :: Libraries :: Python Modules
Requires-Python: <4.0,>=3.8
Requires-Dist: chardet<6.0.0,>=5.1.0
Requires-Dist: click<8.2
Requires-Dist: crispy-bootstrap5<2025.0,>=2024.2
Requires-Dist: django-allauth>=65.4
Requires-Dist: django-ckeditor<7.0.0,>=6.5.1
Requires-Dist: django-compressor>=4.5.1
Requires-Dist: django-crispy-forms<3.0.0,>=2.0
Requires-Dist: django-enum<2.0.0,>=1.2.2
Requires-Dist: django-environ>=0.11.2
Requires-Dist: django-filter<25.0.0,>=24.2
Requires-Dist: django-hijack>=3.6.2
Requires-Dist: django-ipware<8.0.0,>=7.0.1
Requires-Dist: django-polymorphic<5.0,>=4.1.0
Requires-Dist: django-render-static<4.0.0,>=3.1.2
Requires-Dist: django-routines<2.0.0,>=1.1.3
Requires-Dist: django-split-settings<2.0.0,>=1.2.0
Requires-Dist: django-typer<3.0.0,>=2.1.2
Requires-Dist: django-widget-tweaks<2.0.0,>=1.4.12
Requires-Dist: django<5.0,>=4.2.23
Requires-Dist: djangorestframework-gis<2.0.0,>=1.0
Requires-Dist: djangorestframework<4.0.0,>=3.15.2
Requires-Dist: enum-properties<2.0.0,>=1.7.0
Requires-Dist: geojson<4.0.0,>=3.1.0
Requires-Dist: importlib-resources>1.3.0
Requires-Dist: jinja2<4.0.0,>=3.1.2
Requires-Dist: lxml<6.0.0,>=5.2.1
Requires-Dist: packaging>=24.2
Requires-Dist: pillow<11.0.0,>=10.0.0
Requires-Dist: polyline<3.0.0,>=2.0.0
Requires-Dist: psycopg>=3.1
Requires-Dist: python-dateutil<3.0.0,>=2.8.2
Requires-Dist: requests<3.0.0,>=2.32.4
Requires-Dist: rich<15.0.0,>=13.7.1
Requires-Dist: tqdm<5.0.0,>=4.64.1
Provides-Extra: debug
Requires-Dist: django-debug-toolbar<5.0.0,>=4.1.0; extra == 'debug'
Requires-Dist: django-extensions<4.0.0,>=3.1.5; extra == 'debug'
Requires-Dist: ipdb<1.0.0,>=0.13.13; extra == 'debug'
Provides-Extra: gunicorn
Requires-Dist: gunicorn>=22.0.0; extra == 'gunicorn'
